lmfunctions/__init__.py
lmfunctions/backends/__init__.py
lmfunctions/backends/litellm.py
lmfunctions/backends/llamacpp.py
lmfunctions/backends/transformers.py
lmfunctions/backends/vllm.py
lmfunctions/base.py
lmfunctions/chat.py
lmfunctions/default.py
lmfunctions/eventmanager.py
lmfunctions/handlers/__init__.py
lmfunctions/handlers/logging.py
lmfunctions/handlers/otelevent.py
lmfunctions/handlers/panelprint.py
lmfunctions/handlers/print.py
lmfunctions/lmfunc.py
lmfunctions/lmhub.py
lmfunctions/managers/__init__.py
lmfunctions/managers/consolerich.py
lmfunctions/managers/filelog.py
lmfunctions/managers/panelprint.py
lmfunctions/managers/timeevents.py
lmfunctions/managers/tokenstream.py
lmfunctions/message.py
lmfunctions/metaprompt.jinja
lmfunctions/retrypolicy.py
lmfunctions/utils/__init__.py
lmfunctions/utils/cuda_check.py
lmfunctions/utils/dictutils.py
lmfunctions/utils/importutils.py
lmfunctions/utils/panelprint.py
lmfunctions/utils/pydantic.py
lmfunctions/utils/tracing.py
lmfunctions-0.2.2.dist-info/LICENSE
lmfunctions-0.2.2.dist-info/METADATA
lmfunctions-0.2.2.dist-info/WHEEL
lmfunctions-0.2.2.dist-info/RECORD
