Metadata-Version: 2.3
Name: lmfunctions
Version: 0.2.2
Summary: Python functions backed by language models
License: MIT
Author: Francesco Dinuzzo
Requires-Python: >=3.10,<4.0
Classifier: License :: OSI Approved :: MIT License
Classifier: Programming Language :: Python :: 3
Classifier: Programming Language :: Python :: 3.10
Classifier: Programming Language :: Python :: 3.11
Classifier: Programming Language :: Python :: 3.12
Classifier: Programming Language :: Python :: 3.13
Requires-Dist: aiohttp (>=3.9.5,<4.0.0)
Requires-Dist: datamodel-code-generator (>=0.25.5)
Requires-Dist: fsspec (>=2024.3.1,<2025.0.0)
Requires-Dist: huggingface-hub (>=0.23.2,<0.30.0)
Requires-Dist: jinja2 (>=3.1.4,<4.0.0)
Requires-Dist: lm-format-enforcer (>=0.10.2,<0.11.0)
Requires-Dist: openai (>=1.16.2,<2.0.0)
Requires-Dist: opentelemetry-sdk (>=1.25.0,<2.0.0)
Requires-Dist: pandas (>=2.2.2,<3.0.0)
Requires-Dist: pydantic (>=2.6.0,<3.0.0)
Requires-Dist: pyyaml (>=6.0.1,<7.0.0)
Requires-Dist: requests (>=2.32.3,<3.0.0)
Requires-Dist: rich (>=13.6.0,<14.0.0)
Requires-Dist: tenacity (>=8.2.3,<10.0.0)
